pybiginteger.cpython-314-aarch64-linux-musl.so
pybiginteger.libs/libgcc_s-2d945d6c.so.1
pybiginteger.libs/libstdc++-85f2cd6d.so.6.0.33
pybiginteger-1.3.5.dist-info/METADATA
pybiginteger-1.3.5.dist-info/WHEEL
pybiginteger-1.3.5.dist-info/top_level.txt
pybiginteger-1.3.5.dist-info/RECORD
pybiginteger-1.3.5.dist-info/licenses/LICENSE
pybiginteger-1.3.5.dist-info/sboms/auditwheel.cdx.json
