Metadata-Version: 2.4
Name: pybiginteger
Version: 1.3.5
Summary: C++ port of the C# BigInteger class
Home-page: https://github.com/CityOfZion/BigIntegerCpp
Author: Erik van den Brink (ixje), merl111
Author-email: erik@coz.io
Classifier: Development Status :: 5 - Production/Stable
Classifier: Intended Audience :: Developers
Classifier: Programming Language :: C++
License-File: LICENSE
Dynamic: author
Dynamic: author-email
Dynamic: classifier
Dynamic: description
Dynamic: description-content-type
Dynamic: home-page
Dynamic: license-file
Dynamic: summary
